fastcopy/__init__.py
fastcopy/client.py
fastcopy/config.py
fastcopy/network.py
fastcopy/server.py
fastcopy/transfer.py
fastcopy-0.1.8.dist-info/LICENSE
fastcopy-0.1.8.dist-info/METADATA
fastcopy-0.1.8.dist-info/WHEEL
fastcopy-0.1.8.dist-info/entry_points.txt
fastcopy-0.1.8.dist-info/top_level.txt
fastcopy-0.1.8.dist-info/RECORD
