Metadata-Version: 2.1
Name: fastcopy
Version: 0.1.8
Summary: A multi-threaded file transfer tool over SSH. The goal is to replace SCP.
Home-page: https://github.com/seamile/FastCopy
Author: Seamile
Author-email: lanhuermao@gmail.com
License: UNKNOWN
Platform: UNKNOWN
Classifier: Programming Language :: Python :: 3
Classifier: License :: OSI Approved :: MIT License
Classifier: Operating System :: MacOS :: MacOS X
Classifier: Operating System :: POSIX
Classifier: Topic :: Internet
Classifier: Topic :: Utilities
Requires-Python: >=3.6
License-File: LICENSE
Requires-Dist: paramiko (>=2.7.2)
Requires-Dist: python-daemon (>=2.3.0)
Requires-Dist: rich (>=10.6.0)
